[{"d":"0228","sev":"HIGH","sc":58,"dl":3045,"cx":101,"wp":339700,"apt":[{"c":"ГѓВўГ‚ВЂГ‚В”","dl":0,"cx":0,"s":"Normal operations ГѓВўГ‚ВЂГ‚В” no airport specifics available"}],"cause":"Winter storm system across Southeast + DHS shutdown TSA staffing pressure","ota":"HIGH","fwd":"Residual disruption through Mar 1; TSA staffing gaps persist.","conf":"PARTIAL"},{"d":"0301","sev":"MODERATE","sc":28,"dl":2100,"cx":90,"wp":225000,"apt":[{"c":"ORD","dl":198,"cx":12,"s":"Residual winter storm"},{"c":"JFK","dl":145,"cx":8,"s":"NE corridor winds"},{"c":"EWR","dl":133,"cx":6,"s":"NE corridor winds"}],"cause":"Residual winter storm effects + NE corridor winds","ota":"MODERATE","fwd":"Conditions improving; spring break travel builds.","conf":"PARTIAL"},{"d":"0305","sev":"MODERATE","sc":34,"dl":2420,"cx":115,"wp":292300,"apt":[{"c":"ORD","dl":210,"cx":18,"s":"Weather/staffing"},{"c":"ATL","dl":178,"cx":12,"s":"Weather"},{"c":"DFW","dl":155,"cx":9,"s":"Weather"}],"cause":"Spring storm development + TSA staffing shortages Day 10","ota":"MODERATE","fwd":"Spring storm activity building through weekend.","conf":"PARTIAL"},{"d":"0307","sev":"HIGH","sc":55,"dl":4100,"cx":189,"wp":492950,"apt":[{"c":"ORD","dl":389,"cx":42,"s":"Severe thunderstorms"},{"c":"ATL","dl":267,"cx":28,"s":"Thunderstorms"},{"c":"DFW","dl":234,"cx":19,"s":"Thunderstorms"}],"cause":"Major spring storm system + TSA staffing shortages (Day 12) + peak weekend volume","ota":"HIGH","fwd":"Storm exits Mon; residual crew repositioning through Tue.","conf":"PARTIAL"},{"d":"0310","sev":"MODERATE","sc":36,"dl":2540,"cx":122,"wp":307180,"apt":[{"c":"ORD","dl":228,"cx":19,"s":"Weather/staffing"},{"c":"ATL","dl":189,"cx":14,"s":"Weather"},{"c":"DFW","dl":167,"cx":10,"s":"Weather"}],"cause":"Spring storms developing + TSA staffing gaps Day 15","ota":"MODERATE","fwd":"Storm strengthening into weekend; elevated disruption expected.","conf":"PARTIAL"},{"d":"0311","sev":"HIGH","sc":52,"dl":3780,"cx":165,"wp":447170,"apt":[{"c":"ORD","dl":334,"cx":36,"s":"Thunderstorms"},{"c":"ATL","dl":245,"cx":22,"s":"Thunderstorms"},{"c":"DFW","dl":212,"cx":18,"s":"Thunderstorms"}],"cause":"Spring thunderstorm system across Midwest/South + TSA gaps","ota":"HIGH","fwd":"Storm clearing Sun; operational recovery Mon-Tue.","conf":"PARTIAL"},{"d":"0316","sev":"HIGH","sc":57,"dl":4280,"cx":192,"wp":509780,"apt":[{"c":"MCO","dl":378,"cx":35,"s":"Spring Break surge"},{"c":"FLL","dl":289,"cx":28,"s":"Spring Break surge"},{"c":"ATL","dl":245,"cx":22,"s":"Weather+volume"}],"cause":"Spring Break peak weekend + weather + TSA staffing shortages Day 21","ota":"HIGH","fwd":"Peak Spring Break week; expect elevated OTA contacts through Mar 22.","conf":"PARTIAL"},{"d":"0321","sev":"HIGH","sc":58,"dl":4320,"cx":196,"wp":516380,"apt":[{"c":"MCO","dl":389,"cx":36,"s":"Spring Break return"},{"c":"FLL","dl":298,"cx":27,"s":"Spring Break return"},{"c":"ATL","dl":256,"cx":23,"s":"Storm+volume"}],"cause":"Spring Break return weekend surge + storm systems + TSA staffing gaps","ota":"HIGH","fwd":"Return peak ends Sunday; near-normal by Mon-Tue.","conf":"PARTIAL"},{"d":"0323","sev":"MODERATE","sc":38,"dl":2340,"cx":128,"wp":298200,"apt":[{"c":"ORD","dl":245,"cx":22,"s":"Spring Break/storms"},{"c":"DFW","dl":189,"cx":15,"s":"Thunderstorms"},{"c":"ATL","dl":167,"cx":11,"s":"Weather"}],"cause":"Spring Break week peak + thunderstorm activity across Midwest","ota":"MODERATE","fwd":"Spring Break volume continues through Mar 29.","conf":"PARTIAL"},{"d":"0324","sev":"MODERATE","sc":36,"dl":2490,"cx":118,"wp":300620,"apt":[{"c":"ORD","dl":218,"cx":19,"s":"Thunderstorms"},{"c":"ATL","dl":178,"cx":13,"s":"Weather"},{"c":"DFW","dl":156,"cx":10,"s":"Weather"}],"cause":"Spring storms + Spring Break travel + DHS shutdown Day 29","ota":"MODERATE","fwd":"Storm activity continues through weekend.","conf":"PARTIAL"},{"d":"0326","sev":"HIGH","sc":56,"dl":4180,"cx":188,"wp":497020,"apt":[{"c":"MCO","dl":367,"cx":33,"s":"Spring Break return"},{"c":"ATL","dl":278,"cx":25,"s":"Storm+volume"},{"c":"ORD","dl":245,"cx":21,"s":"Thunderstorms"}],"cause":"Spring Break return peak + severe storms + TSA staffing shortages","ota":"HIGH","fwd":"Spring Break return surge tapering Mon; storms clearing.","conf":"PARTIAL"},{"d":"0328","sev":"HIGH","sc":53,"dl":3890,"cx":178,"wp":471100,"apt":[{"c":"ORD","dl":312,"cx":28,"s":"Spring Break+storms"},{"c":"ATL","dl":267,"cx":19,"s":"Thunderstorms"},{"c":"DFW","dl":234,"cx":16,"s":"Thunderstorms"}],"cause":"Spring Break peak + severe Midwest thunderstorms + TSA staffing shortages","ota":"HIGH","fwd":"Spring Break winds down Apr 1; storm system exits by weekend.","conf":"PARTIAL"},{"d":"0330","sev":"MODERATE","sc":40,"dl":2820,"cx":127,"wp":336430,"apt":[{"c":"ORD","dl":245,"cx":20,"s":"Post-Spring Break"},{"c":"ATL","dl":189,"cx":15,"s":"Weather"},{"c":"DFW","dl":165,"cx":11,"s":"Weather"}],"cause":"Post-Spring Break normalization + weather systems + DHS shutdown Day 35","ota":"MODERATE","fwd":"Stable conditions; Easter travel building.","conf":"PARTIAL"},{"d":"0331","sev":"MODERATE","sc":38,"dl":2640,"cx":118,"wp":314020,"apt":[{"c":"ORD","dl":228,"cx":18,"s":"Weather"},{"c":"ATL","dl":178,"cx":13,"s":"Weather"},{"c":"DFW","dl":156,"cx":10,"s":"Weather"}],"cause":"Weather systems + DHS shutdown TSA staffing shortages (Day 36)","ota":"MODERATE","fwd":"Easter weekend approaches; expect significant volume build Apr 2-3.","conf":"PARTIAL"},{"d":"0401","sev":"MODERATE","sc":45,"dl":3180,"cx":150,"wp":349500,"apt":[{"c":"DFW","dl":278,"cx":25,"s":"Weather+Easter"},{"c":"ORD","dl":245,"cx":20,"s":"Weather"},{"c":"MCO","dl":212,"cx":17,"s":"Easter surge"}],"cause":"Easter travel surge begins + weather systems + DHS shutdown TSA staffing","ota":"MODERATE","fwd":"Easter peak builds through Fri; expect HIGH conditions Apr 3-6.","conf":"PARTIAL"},{"d":"0402","sev":"MODERATE","sc":43,"dl":2224,"cx":119,"wp":277510,"apt":[{"c":"ORD","dl":278,"cx":42,"s":"Rain & low clouds + TSA gaps"},{"c":"LGA","dl":245,"cx":17,"s":"Rain & low clouds"},{"c":"JFK","dl":122,"cx":8,"s":"Rain & low clouds"}],"cause":"Spring storms compounded by TSA staffing shortages from ongoing DHS shutdown","ota":"MODERATE","fwd":"TSA back pay flowing via executive order but staffing gaps persist.","conf":"PARTIAL"},{"d":"0403","sev":"CRITICAL","sc":88,"dl":6232,"cx":801,"wp":1081530,"apt":[{"c":"ORD","dl":1247,"cx":419,"s":"Thunderstorms, tornado risk"},{"c":"MCO","dl":300,"cx":21,"s":"Thunderstorms"},{"c":"MIA","dl":260,"cx":10,"s":"Network congestion"}],"cause":"Severe thunderstorms & tornado risk at ORD + Easter/Good Friday peak + TSA shutdown","ota":"HIGH","fwd":"Residual delays Sat Apr 4 as ORD repositions aircraft/crews.","conf":"PARTIAL"},{"d":"0404","sev":"CRITICAL","sc":82,"dl":5500,"cx":460,"wp":794000,"apt":[{"c":"DEN","dl":323,"cx":15,"s":"Low clouds + runway works"},{"c":"ORD","dl":268,"cx":46,"s":"Storm backlog + Easter surge"},{"c":"LAS","dl":208,"cx":12,"s":"Network ripple effects"}],"cause":"Thunderstorm backlog from Good Friday + Easter Saturday peak volume","ota":"HIGH","fwd":"Easter Sunday return travel will spike demand; ORD backlog may persist 24-48 hrs.","conf":"PARTIAL"},{"d":"0405","sev":"CRITICAL","sc":85,"dl":11000,"cx":500,"wp":1315000,"apt":[{"c":"ATL","dl":271,"cx":35,"s":"Severe thunderstorms"},{"c":"ORD","dl":268,"cx":46,"s":"Thunderstorms, FAA ground stops"},{"c":"MIA","dl":150,"cx":25,"s":"Storms & localized flooding"}],"cause":"Severe Easter storms (thunderstorms, heavy rain, flooding) + record holiday passenger volumes","ota":"HIGH","fwd":"Residual disruption Mon-Tue as aircraft/crews reposition.","conf":"PARTIAL"},{"d":"0406","sev":"HIGH","sc":72,"dl":4722,"cx":307,"wp":624530,"apt":[{"c":"LGA","dl":262,"cx":28,"s":"Volume + cascade"},{"c":"MIA","dl":265,"cx":9,"s":"Spring break + Easter + cruise"},{"c":"ORD","dl":238,"cx":4,"s":"Residual storm repositioning"}],"cause":"Easter Monday return surge + cascading effects from 4-day storm sequence since Good Friday","ota":"HIGH","fwd":"Disruptions taper Tue-Wed; residual crew imbalances at ATL, ORD, LGA.","conf":"CONFIRMED"},{"d":"0407","sev":"HIGH","sc":61,"dl":3022,"cx":191,"wp":396130,"apt":[{"c":"MCO","dl":198,"cx":9,"s":"Storm cascades"},{"c":"MIA","dl":197,"cx":9,"s":"Thunderstorms, FAA ground stop"},{"c":"LAX","dl":128,"cx":10,"s":"Low clouds, volume"}],"cause":"Southeast thunderstorms + post-Easter recovery + DHS shutdown TSA staffing gaps (Day 52)","ota":"HIGH","fwd":"Airlines targeting Wed-Thu for near-normal ops. Residual crew repositioning through Wed AM.","conf":"PARTIAL"},{"d":"0408","sev":"HIGH","sc":51,"dl":3440,"cx":114,"wp":383700,"apt":[{"c":"DFW","dl":454,"cx":77,"s":"Storms + AA hub cascade"},{"c":"MIA","dl":384,"cx":6,"s":"Spring thunderstorms"},{"c":"ORD","dl":316,"cx":25,"s":"FAA ground stop, tornado risk"}],"cause":"Post-Easter cascade + Midwest thunderstorms; FAA ground stop at ORD; AA network-wide meltdown","ota":"MODERATE","fwd":"Residual delays Thu as DFW/ORD recover from 6-day cascade.","conf":"PARTIAL"},{"d":"0409","sev":"MODERATE","sc":42,"dl":3025,"cx":63,"wp":313200,"apt":[{"c":"ORD","dl":222,"cx":13,"s":"Storm cascade"},{"c":"JFK","dl":201,"cx":6,"s":"NY metro congestion"},{"c":"MCO","dl":198,"cx":9,"s":"South FL storms"}],"cause":"Eastern US spring storms + Washington Dulles ATC facility issue; SFO runway 1R closure","ota":"MODERATE","fwd":"Residual GDPs into Fri AM; SFO runway constraint continues for weeks.","conf":"CONFIRMED"},{"d":"0410","sev":"MODERATE","sc":32,"dl":1221,"cx":114,"wp":183990,"apt":[{"c":"ATL","dl":144,"cx":28,"s":"Thunderstorms"},{"c":"EWR","dl":133,"cx":5,"s":"High winds, NE corridor"},{"c":"JFK","dl":127,"cx":12,"s":"High winds"}],"cause":"High winds along NE corridor + thunderstorms in FL/TX","ota":"MODERATE","fwd":"Weather pushing east overnight; residual NE delays Saturday AM.","conf":"PARTIAL"},{"d":"0411","sev":"MODERATE","sc":35,"dl":1759,"cx":79,"wp":209660,"apt":[{"c":"LAS","dl":250,"cx":10,"s":"Weather/congestion"},{"c":"MCO","dl":198,"cx":9,"s":"Weather/volume"},{"c":"PHX","dl":163,"cx":2,"s":"Storms"}],"cause":"Spring thunderstorms hitting leisure hubs + post-Easter volume + ATC capacity constraints","ota":"MODERATE","fwd":"DEN high-wind ground stop Sun Apr 12; AA travel waiver for DFW Apr 12.","conf":"PARTIAL"},{"d":"0412","sev":"MODERATE","sc":37,"dl":1910,"cx":135,"wp":259650,"apt":[{"c":"DFW","dl":154,"cx":5,"s":"Wind/congestion"},{"c":"ORD","dl":143,"cx":7,"s":"Weather/congestion"},{"c":"ATL","dl":115,"cx":34,"s":"Storms/cascading"}],"cause":"Thunderstorms/high winds across multiple regions + East Coast congestion; DEN ground stop (3 hrs)","ota":"LOW","fwd":"Spring storm pattern continues mid-week; no major system-wide events next 24 hrs.","conf":"PARTIAL"},{"d":"0413","sev":"MODERATE","sc":46,"dl":1759,"cx":79,"wp":209660,"apt":[{"c":"FLL","dl":300,"cx":22,"s":"Thunderstorms"},{"c":"ORD","dl":157,"cx":7,"s":"Storms, weather waiver"},{"c":"JFK","dl":156,"cx":8,"s":"Storms, NE weather"}],"cause":"Severe thunderstorms across Central/Eastern US + FAA ATC staffing shortages amid gov shutdown (LAX ground stop)","ota":"MODERATE","fwd":"Storm system shifting east; NE airports elevated risk next 24h. ATC staffing strain continues.","conf":"CONFIRMED"},{"d":"0414","sev":"HIGH","sc":52,"dl":2576,"cx":153,"wp":331290,"apt":[{"c":"ORD","dl":386,"cx":14,"s":"Thunderstorms, GDP, transatlantic cancels"},{"c":"ATL","dl":211,"cx":16,"s":"Storms, Delta hub GDP"},{"c":"DEN","dl":161,"cx":8,"s":"High-wind ground stop"}],"cause":"Severe thunderstorm system shifting east from Central US; multiple hub ground delay programs active (ORD, ATL, SFO, TPA)","ota":"HIGH","fwd":"Storm system exits East Coast next 24 hrs; residual delays Wed as crews/aircraft reposition. Improving by Thursday.","conf":"CONFIRMED"},{"d":"0415","sev":"MODERATE","sc":41,"dl":2300,"cx":135,"wp":294750,"apt":[{"c":"ORD","dl":315,"cx":9,"s":"Thunderstorms; FAA ground stop 10:20p-11:45p"},{"c":"CLT","dl":216,"cx":1,"s":"Post-Easter rebooking backlog (AA hub)"},{"c":"DFW","dl":186,"cx":6,"s":"Air traffic congestion; AA/DL/WN elevated"}],"cause":"Thunderstorms at ORD (late-night FAA ground stop) + continued post-Easter network recovery","ota":"MODERATE","fwd":"Apr 16 flagged as earliest realistic clean national day; ORD storm system clearing east by morning push; gradual normalization.","conf":"PARTIAL"},{"d":"0416","sev":"NORMAL","sc":15,"dl":1440,"cx":75,"wp":178350,"apt":[{"c":"ГѓВўГ‚ВЂГ‚В”","dl":0,"cx":0,"s":"Normal operations ГѓВўГ‚ВЂГ‚В” no airport specifics available"}],"cause":"Normal operations ГѓВўГ‚ВЂГ‚В” no active FAA ground programs","ota":"LOW","fwd":"No active FAA ground programs. Normal operational outlook.","conf":"FAA-API"},{"d":"0417","sev":"HIGH","sc":55,"dl":3200,"cx":160,"wp":392000,"apt":[{"c":"ORD","dl":867,"cx":105,"s":"Historic flooding + FAA ground stop"},{"c":"SFO","dl":224,"cx":7,"s":"Low ceiling fog + FAA runway cap"},{"c":"BOS","dl":210,"cx":7,"s":"Weather + Lufthansa cancels"}],"al":"OO|UA|MQ|B6","cause":"ORD historic flooding (rainiest April day in decade) triggered FAA ground stop; SFO Runway 1R closure compounding (arrivals capped 36/hr); DHS shutdown TSA staffing gaps persist","ota":"HIGH","fwd":"ORD terminal flooding recovery expected 24-48 hrs; SFO runway constraints ongoing through Oct.","conf":"PARTIAL"},{"d":"0418","sev":"HIGH","sc":61,"dl":4313,"cx":338,"wp":607870,"apt":[{"c":"ORD","dl":531,"cx":187,"s":"77-year rainfall aftermath"},{"c":"LAS","dl":490,"cx":51,"s":"Volume + cascading"},{"c":"MSP","dl":300,"cx":7,"s":"Network congestion"},{"c":"LAX","dl":250,"cx":10,"s":"Volume congestion"}],"al":"WN|AA|DL|UA","cause":"ORD 77-year rainfall aftermath (531d/187c); 2nd-worst national total of spring crisis. WN led all carriers (1,030d). FAA ordered ORD flight cap (2,708/day May 17-Oct 24)","ota":"HIGH","fwd":"FAA ORD flight cap announced. DHS shutdown TSA funds depleting. SFO runway closure cascading.","conf":"CONFIRMED"},{"d":"0419","sev":"MODERATE","sc":45,"dl":3052,"cx":109,"wp":345530,"apt":[{"c":"DFW","dl":708,"cx":7,"s":"Congestion + AA hub cascade"},{"c":"ORD","dl":320,"cx":45,"s":"Flooding recovery + cancels"},{"c":"ATL","dl":136,"cx":9,"s":"Volume"},{"c":"JFK","dl":108,"cx":4,"s":"Volume congestion"}],"al":"AA|WN|OO|DL","cause":"DFW 700+ delays (worst single-airport day); ORD flooding recovery ongoing; ATC staffing constraints at NY TRACON + SoCal TRACON","ota":"MODERATE","fwd":"ORD FAA summer flight cap announced; SFO capacity constraints ongoing; DHS shutdown unresolved.","conf":"CONFIRMED"},{"d":"0420","sev":"MODERATE","sc":50,"dl":4231,"cx":79,"wp":432140,"apt":[{"c":"ORD","dl":337,"cx":6,"s":"Severe thunderstorms"},{"c":"ATL","dl":290,"cx":4,"s":"Thunderstorms + wind"},{"c":"JFK","dl":123,"cx":5,"s":"Storms"},{"c":"DTW","dl":121,"cx":13,"s":"Thunderstorms (worst hit)"}],"al":"WN|AA|DL|UA","cause":"Severe thunderstorms, high winds, poor visibility nationwide; WN 730d, AA 542d. Tightly planned rotations + ATC staffing gaps slowed recovery","ota":"MODERATE","fwd":"Storm system continuing into Mon; crew/aircraft repositioning compounding delays.","conf":"CONFIRMED"},{"d":"0421","sev":"MODERATE","sc":44,"dl":3002,"cx":105,"wp":338430,"apt":[{"c":"SFO","dl":368,"cx":60,"s":"Runway 1R closure cascade"},{"c":"ATL","dl":180,"cx":5,"s":"Network congestion"},{"c":"BOS","dl":143,"cx":0,"s":"Operational slowdowns"},{"c":"JFK","dl":76,"cx":5,"s":"Volume"}],"al":"OO|UA|AA|DL|9E","cause":"SFO Runway 1R closure cascading nationwide (368d/60c epicenter); SkyWest 52cx rippled through UA/DL/AA/AS partner networks; ATC staffing strain at SoCal/NY TRACONs","ota":"MODERATE","fwd":"SFO runway constraints ongoing through Oct 2; regional carrier stress elevating cancels system-wide.","conf":"CONFIRMED"},{"d":"0422","sev":"MODERATE","sc":33,"dl":1762,"cx":46,"wp":188480,"apt":[{"c":"ORD","dl":152,"cx":5,"s":"Residual congestion"},{"c":"LAX","dl":121,"cx":2,"s":"Volume"},{"c":"JFK","dl":63,"cx":5,"s":"Volume"}],"al":"WN|9E|AA|DL","cause":"Significant recovery ГўВЂВ” 62% reduction from Apr 18 peak. Structural pressures (ATC shortage, SFO closure, DHS/TSA crisis) persist but weather cooperating","ota":"LOW","fwd":"Recovery trend encouraging but system running on thin margins; ATC staffing and DHS shutdown unresolved.","conf":"CONFIRMED"},{"d":"0423","sev":"MODERATE","sc":40,"dl":2741,"cx":52,"wp":280490,"apt":[{"c":"DFW","dl":198,"cx":8,"s":"Hub congestion"},{"c":"ORD","dl":180,"cx":7,"s":"Volume + ATC staffing"},{"c":"DTW","dl":95,"cx":12,"s":"Cancellations lead"},{"c":"LAX","dl":113,"cx":3,"s":"Volume"}],"al":"WN|AA|UA|OO|9E","cause":"Regression from recovery ГўВЂВ” DFW/ORD hub bottlenecks + ATC staffing constraints (NY/SoCal TRACONs critically understaffed) + SkyWest/Endeavor regional carrier cascading","ota":"MODERATE","fwd":"System under structural pressure from ATC shortage, SFO closure, DHS shutdown; no major weather but systemic stress persists.","conf":"PARTIAL"},{"d":"0424","sev":"MODERATE","sc":37,"dl":2181,"cx":49,"wp":228140,"apt":[{"c":"JFK","dl":81,"cx":4,"s":"NY TRACON ATC constraints"},{"c":"MIA","dl":95,"cx":6,"s":"Volume + weather"},{"c":"IAD","dl":72,"cx":3,"s":"ATC + storms"}],"al":"AA|OO|UA|DL","cause":"Structural ATC staffing deficit + DHS/TSA shutdown strain + spring weather (storms DFW, wind LGA, low vis DEN); AA 236d, SkyWest 209d cascading through partner networks","ota":"MODERATE","fwd":"Weekend volume building; ATC and TSA structural issues unresolved. DHS warns funds run out early May.","conf":"PARTIAL"},{"d":"0425","sev":"MODERATE","sc":32,"dl":1639,"cx":56,"wp":183910,"apt":[{"c":"ORD","dl":494,"cx":6,"s":"Weather recovery + fueling failure"},{"c":"SAN","dl":170,"cx":0,"s":"Volume congestion"},{"c":"ATL","dl":150,"cx":13,"s":"Volume + weather"},{"c":"JFK","dl":92,"cx":9,"s":"Volume congestion"}],"al":"DL|UA|AA|WN|B6","cause":"ORD fueling system failure (494d) + Saturday lower volume offset by structural ATC/TSA constraints; SFO closure continues to reduce network capacity","ota":"LOW","fwd":"Sunday volumes lighter; ORD fueling resolved. ATC and DHS shutdown remain unresolved structural risks.","conf":"PARTIAL"},{"d":"0426","sev":"MODERATE","sc":30,"dl":1500,"cx":80,"wp":187000,"apt":[{"c":"TPA","dl":79,"cx":8,"s":"Cascading delays to LGA/JFK/ORD"},{"c":"JFK","dl":72,"cx":7,"s":"NY TRACON constraints"},{"c":"EWR","dl":65,"cx":5,"s":"NY metro congestion"}],"al":"DL|AA|UA|B6","cause":"Sunday lower volume but TPA cascading delays stranded 800+ travelers; NY metro (JFK/EWR) congestion from ATC staffing gaps at NY TRACON; DHS/TSA shutdown ongoing","ota":"LOW","fwd":"Monday volume surge expected; LGA wind vulnerability flagged. DHS funds depleting.","conf":"ESTIMATED"},{"d":"0427","sev":"HIGH","sc":56,"dl":4470,"cx":222,"wp":546600,"apt":[{"c":"ORD","dl":1021,"cx":152,"s":"Thunderstorms + volume surge"},{"c":"DFW","dl":390,"cx":21,"s":"Storms + AA hub cascade"},{"c":"LGA","dl":180,"cx":25,"s":"FAA ground stop (high winds)"}],"al":"OO|WN|AA|UA|9E|DL","cause":"LGA FAA ground stop (high winds) cascaded nationwide; ORD 1,021d/152c worst single-airport day; ATC staffing at 77% of target; DHS/TSA shutdown compounding","ota":"HIGH","fwd":"ORD and LGA recovery will take 24-48 hrs. DHS warns TSA funds exhausted by early May. ATC crisis deepening.","conf":"CONFIRMED"},{"d":"0428","sev":"CRITICAL","sc":81,"dl":5581,"cx":353,"wp":731740,"apt":[{"c":"ORD","dl":1228,"cx":260,"s":"Severe thunderstorms, ground stop"},{"c":"DEN","dl":383,"cx":6,"s":"Cascade + low visibility"},{"c":"PHX","dl":304,"cx":5,"s":"Cascade from ORD"},{"c":"ATL","dl":292,"cx":10,"s":"Cascade from ORD"},{"c":"DFW","dl":200,"cx":21,"s":"Severe storms, tornado watch"},{"c":"MDW","dl":180,"cx":12,"s":"Severe thunderstorms"}],"al":"WN|AA|OO|UA|DL","cause":"Severe thunderstorms Chicago ground stop + DFW tornado watch","ota":"HIGH","fwd":"DFW cancellation surge expected Apr 29 from aircraft repositioning; residual ORD delays; continued Central US storm risk","conf":"CONFIRMED"}]